nyc_intersection_geocoder/__init__.py
nyc_intersection_geocoder/geocoder.py
nyc_intersection_geocoder-0.0.4.dist-info/LICENSE
nyc_intersection_geocoder-0.0.4.dist-info/METADATA
nyc_intersection_geocoder-0.0.4.dist-info/WHEEL
nyc_intersection_geocoder-0.0.4.dist-info/top_level.txt
nyc_intersection_geocoder-0.0.4.dist-info/RECORD
