Metadata-Version: 2.1
Name: nyc-intersection-geocoder
Version: 0.0.4
Summary: Package to help geocode NYC intersections with OSMPythonTools.
Home-page: https://github.com/wplam107/nyc_intersection_geocoder
Author: Wayne Lam
Author-email: w.p.lam107@gmail.com
License: UNKNOWN
Project-URL: Bug Tracker, https://github.com/wplam107/nyc_intersection_geocoder/issues
Platform: UNKNOWN
Classifier: Programming Language :: Python :: 3
Classifier: License :: OSI Approved :: MIT License
Classifier: Operating System :: OS Independent
Requires-Python: >=3.6
License-File: LICENSE
Requires-Dist: OSMPythonTools
Requires-Dist: shapely
